<struktogramm titel='MinMaxMitt, Cassebaum 2008' rueckgabetyp = 'void' code = 'main'><block text=''><element type= 'anweisung'><content type='text'>i = 0</content><content type='code'></content></element><element type='kopfschleife'><content type='text'>while i&lt;10</content><content type='code'></content><block text=''><element type= 'anweisung'><content type='text'>a[i]=random[100]</content><content type='code'></content></element><element type= 'anweisung'><content type='text'>A:BS ; a[i]</content><content type='code'></content></element><element type= 'anweisung'><content type='text'>i := i+1</content><content type='code'></content></element></block></element><element type= 'anweisung'><content type='text'>              ma := mi := su := a[0]                     </content><content type='code'></content></element><element type= 'anweisung'><content type='text'>i := 1</content><content type='code'></content></element><element type='kopfschleife'><content type='text'>while i&lt;10</content><content type='code'></content><block text=''><element type='verzweigung'><content type='text'>a[i] &gt; ma ?</content><content type='code'></content><block text=''><element type= 'anweisung'><content type='text'>ma := a[i]</content><content type='code'></content></element></block><block text=''></block></element><element type='verzweigung'><content type='text'>a[i] &lt; mi ?</content><content type='code'></content><block text=''><element type= 'anweisung'><content type='text'>mi := a[i]</content><content type='code'></content></element></block><block text=''></block></element><element type= 'anweisung'><content type='text'>su := su + a[i]</content><content type='code'></content></element></block></element><element type= 'anweisung'><content type='text'>A:BS ; ma,mi, su / i</content><content type='code'></content></element></block></struktogramm>